tlbpy/__init__.py
tlbpy/cnf_parser.py
tlbpy/duration.py
tlbpy/helloworld.py
tlbpy/path.py
tlbpy/talk.py
tlbpy/test.py
tlbpy/rl_algos/__init__.py
tlbpy/rl_algos/ac.py
tlbpy/rl_algos/monte_carlo.py
tlbpy/rl_algos/pda.py
tlbpy/rl_algos/qlearning.py
tlbpy/rl_algos/rl_algo.py
tlbpy/rl_algos/spg.py
tlbpy/rl_algos/utils.py
tlbpy/rl_algos/tests/__init__.py
tlbpy/rl_algos/tests/test_pda.py
tlbpy/rl_algos/tests/test_qlearning.py
tlbpy/rl_algos/tests/test_spg.py
tlbpy-0.0.19.dist-info/LICENSE
tlbpy-0.0.19.dist-info/METADATA
tlbpy-0.0.19.dist-info/WHEEL
tlbpy-0.0.19.dist-info/entry_points.txt
tlbpy-0.0.19.dist-info/top_level.txt
tlbpy-0.0.19.dist-info/RECORD
