Metadata-Version: 2.1
Name: tlbpy
Version: 0.0.19
Summary: My personnal toolbox for python
Home-page: https://github.com/Guitheg/tlbpy
Author: Guitheg
Author-email: UNKNOWN
License: MIT
Platform: UNKNOWN
Classifier: Programming Language :: Python
Classifier: Development Status :: 2 - Pre-Alpha
Classifier: License :: OSI Approved :: MIT License
Classifier: Natural Language :: French
Classifier: Operating System :: OS Independent
Classifier: Programming Language :: Python :: 3 :: Only
Classifier: Topic :: Education
